django_undeletable/__init__.py
django_undeletable/apps.py
django_undeletable/models.py
django_undeletable-1.1.2.dist-info/AUTHORS.rst
django_undeletable-1.1.2.dist-info/LICENSE
django_undeletable-1.1.2.dist-info/METADATA
django_undeletable-1.1.2.dist-info/WHEEL
django_undeletable-1.1.2.dist-info/top_level.txt
django_undeletable-1.1.2.dist-info/RECORD
