Metadata-Version: 2.1
Name: django-undeletable
Version: 1.1.2
Summary: Undeletable Django models
Home-page: https://github.com/kakulukia/django-undeletable
Download-URL: https://github.com/kakulukia/django-undeletable/tarball/1.1.2
Author: Andy Grabow
Author-email: andy@freilandkiwis.de
License: MIT
Keywords: orm,undelete,shadow db
Platform: UNKNOWN
Classifier: Development Status :: 5 - Production/Stable
Classifier: Framework :: Django
Classifier: Framework :: Django :: 1.10
Classifier: Intended Audience :: Developers
Classifier: License :: OSI Approved :: MIT License
Classifier: Operating System :: OS Independent
Classifier: Programming Language :: Python
Classifier: Natural Language :: English
Classifier: Programming Language :: Python :: 3
Classifier: Programming Language :: Python :: 3.3
Classifier: Programming Language :: Python :: 3.4
Classifier: Programming Language :: Python :: 3.5
Classifier: Programming Language :: Python :: 3.6
Classifier: Programming Language :: Python :: 3.7
Classifier: Programming Language :: Python :: 3.8
Classifier: Programming Language :: Python :: 3.9
Classifier: Programming Language :: Python :: 3.10
Classifier: Framework :: Django :: 2.0
Classifier: Framework :: Django :: 3.0
Classifier: Framework :: Django :: 4.0
Classifier: Topic :: Software Development :: Libraries :: Python Modules
Requires-Python: >=3.3
License-File: LICENSE
License-File: AUTHORS.rst
Requires-Dist: Django (>=2.0.13)
